printable/__init__.py
printable/__main__.py
printable-0.3.7.dist-info/METADATA
printable-0.3.7.dist-info/WHEEL
printable-0.3.7.dist-info/entry_points.txt
printable-0.3.7.dist-info/top_level.txt
printable-0.3.7.dist-info/RECORD
