Metadata-Version: 2.4
Name: printable
Version: 0.3.7
Summary: functions help for print tabular data
Home-page: https://github.com/weaming/printable
Author: weaming
Author-email: garden.yuen@gmail.com
Project-URL: Bug Reports, https://github.com/weaming/printable
Project-URL: Source, https://github.com/weaming/printable
Keywords: math
Requires-Dist: data-process==0.3.*
Dynamic: author
Dynamic: author-email
Dynamic: description
Dynamic: description-content-type
Dynamic: home-page
Dynamic: keywords
Dynamic: project-url
Dynamic: requires-dist
Dynamic: summary
